bsdownloader/__init__.py
bsdownloader/__main__.py
bsdownloader/config.py
bsdownloader/download.py
bsdownloader/gui.py
bsdownloader/http_get.py
bsdownloader/image.py
bsdownloader/song.py
bsdownloader/timed_progress.py
bsdownloader/user.py
bsdownloader-0.2.2.dist-info/LICENSE
bsdownloader-0.2.2.dist-info/METADATA
bsdownloader-0.2.2.dist-info/WHEEL
bsdownloader-0.2.2.dist-info/entry_points.txt
bsdownloader-0.2.2.dist-info/top_level.txt
bsdownloader-0.2.2.dist-info/RECORD
