Metadata-Version: 2.1
Name: bsdownloader
Version: 0.2.2
Summary: Song downloader for Beat Saber
Home-page: https://github.com/Norne9/beatsaber-downloader
Author: Aleksey Pestov
Author-email: aleksey191295@gmail.com
License: UNKNOWN
Platform: UNKNOWN
Classifier: Programming Language :: Python :: 3
Classifier: License :: OSI Approved :: BSD License
Classifier: Operating System :: OS Independent
Requires-Python: >=3.7
Requires-Dist: beautifulsoup4 (>=4.8.1)
Requires-Dist: requests (>=2.22.0)
Requires-Dist: wxPython (>=4.0.7.post2)
Requires-Dist: cloudscraper (>=1.2.18)
